original.py
original.py-0.0.2.dist-info/METADATA
original.py-0.0.2.dist-info/WHEEL
original.py-0.0.2.dist-info/entry_points.txt
original.py-0.0.2.dist-info/top_level.txt
original.py-0.0.2.dist-info/RECORD
