Metadata-Version: 2.1
Name: original.py
Version: 0.0.2
Summary: A package for visualization of aggregate data of players in "original"
Home-page: https://github.com/Yusukemaegami/ds-tokuron
Author: Yusuke Yamauchi
Author-email: s2022033@stu.musashino-u.ac.jp
License: UNKNOWN
Project-URL: Bug Tracker, https://github.com/Yusukemaegami/ds-tokuron
Platform: UNKNOWN
Classifier: Programming Language :: Python :: 3
Classifier: License :: OSI Approved :: MIT License
Classifier: Operating System :: OS Independent
Requires-Python: >=3.8
